jupyslack/__init__.py
jupyslack-0.2.1.dist-info/LICENSE
jupyslack-0.2.1.dist-info/METADATA
jupyslack-0.2.1.dist-info/WHEEL
jupyslack-0.2.1.dist-info/top_level.txt
jupyslack-0.2.1.dist-info/RECORD
