Metadata-Version: 2.1
Name: jupyslack
Version: 0.2.1
Summary: Slack integration to notebooks
Home-page: https://github.com/Achuttarsing/jupyslack
Author: Adrien Chuttarsing
Author-email: adrien.chuttarsing@gmail.com
License: MIT
Keywords: ipython slack notebook jupyslack
Platform: UNKNOWN
Classifier: Development Status :: 3 - Alpha
Classifier: Intended Audience :: Developers
Classifier: Framework :: IPython
Classifier: Programming Language :: Python
Classifier: Topic :: Utilities
Requires-Dist: ipython
Requires-Dist: requests
